Vivado_basic/spi_ref.v
`timescale 1ns / 1ps


module SPI_Master
  #(parameter SPI_MODE = 0,
    parameter CLKS_PER_HALF_BIT = 2)
  (
   // Control/Data Signals,
   input        i_Rst_L,     // FPGA Reset
   input        i_Clk,       // FPGA Clock
   
   // TX (MOSI) Signals
   input [7:0]  i_TX_Byte,        // Byte to transmit on MOSI
   input        i_TX_DV,          // Data Valid Pulse with i_TX_Byte
   output reg   o_TX_Ready,       // Transmit Ready for next byte
   
   // RX (MISO) Signals
   output reg       o_RX_DV,     // Data Valid pulse (1 clock cycle)
   output reg [7:0] o_RX_Byte,   // Byte received on MISO

   // SPI Interface
   output reg o_SPI_Clk,
   input      i_SPI_MISO,
   output reg o_SPI_MOSI
   );

  // SPI Interface (All Runs at SPI Clock Domain)
  wire w_CPOL;     // Clock polarity
  wire w_CPHA;     // Clock phase

  reg [$clog2(CLKS_PER_HALF_BIT*2)-1:0] r_SPI_Clk_Count;
  reg r_SPI_Clk;
  reg [4:0] r_SPI_Clk_Edges;
  reg r_Leading_Edge;
  reg r_Trailing_Edge;
  reg       r_TX_DV;
  reg [7:0] r_TX_Byte;

  reg [2:0] r_RX_Bit_Count;
  reg [2:0] r_TX_Bit_Count;

  // CPOL: Clock Polarity
  // CPOL=0 means clock idles at 0, leading edge is rising edge.
  // CPOL=1 means clock idles at 1, leading edge is falling edge.
  assign w_CPOL  = (SPI_MODE == 2) | (SPI_MODE == 3);

  // CPHA: Clock Phase
  // CPHA=0 means the "out" side changes the data on trailing edge of clock
  //              the "in" side captures data on leading edge of clock
  // CPHA=1 means the "out" side changes the data on leading edge of clock
  //              the "in" side captures data on the trailing edge of clock
  assign w_CPHA  = (SPI_MODE == 1) | (SPI_MODE == 3);



  // Purpose: Generate SPI Clock correct number of times when DV pulse comes
  always @(posedge i_Clk or negedge i_Rst_L)
  begin
    if (~i_Rst_L)
    begin
      o_TX_Ready      <= 1'b0;
      r_SPI_Clk_Edges <= 0;
      r_Leading_Edge  <= 1'b0;
      r_Trailing_Edge <= 1'b0;
      r_SPI_Clk       <= w_CPOL; // assign default state to idle state
      r_SPI_Clk_Count <= 0;
    end
    else
    begin

      // Default assignments
      r_Leading_Edge  <= 1'b0;
      r_Trailing_Edge <= 1'b0;
      
      if (i_TX_DV)
      begin
        o_TX_Ready      <= 1'b0;
        r_SPI_Clk_Edges <= 16;  // Total # edges in one byte ALWAYS 16
      end
      else if (r_SPI_Clk_Edges > 0)
      begin
        o_TX_Ready <= 1'b0;
        
        if (r_SPI_Clk_Count == CLKS_PER_HALF_BIT*2-1)
        begin
          r_SPI_Clk_Edges <= r_SPI_Clk_Edges - 1'b1;
          r_Trailing_Edge <= 1'b1;
          r_SPI_Clk_Count <= 0;
          r_SPI_Clk       <= ~r_SPI_Clk;
        end
        else if (r_SPI_Clk_Count == CLKS_PER_HALF_BIT-1)
        begin
          r_SPI_Clk_Edges <= r_SPI_Clk_Edges - 1'b1;
          r_Leading_Edge  <= 1'b1;
          r_SPI_Clk_Count <= r_SPI_Clk_Count + 1'b1;
          r_SPI_Clk       <= ~r_SPI_Clk;
        end
        else
        begin
          r_SPI_Clk_Count <= r_SPI_Clk_Count + 1'b1;
        end
      end  
      else
      begin
        o_TX_Ready <= 1'b1;
      end
      
      
    end // else: !if(~i_Rst_L)
  end // always @ (posedge i_Clk or negedge i_Rst_L)


  // Purpose: Register i_TX_Byte when Data Valid is pulsed.
  // Keeps local storage of byte in case higher level module changes the data
  always @(posedge i_Clk or negedge i_Rst_L)
  begin
    if (~i_Rst_L)
    begin
      r_TX_Byte <= 8'h00;
      r_TX_DV   <= 1'b0;
    end
    else
      begin
        r_TX_DV <= i_TX_DV; // 1 clock cycle delay
        if (i_TX_DV)
        begin
          r_TX_Byte <= i_TX_Byte;
        end
      end // else: !if(~i_Rst_L)
  end // always @ (posedge i_Clk or negedge i_Rst_L)


  // Purpose: Generate MOSI data
  // Works with both CPHA=0 and CPHA=1
  always @(posedge i_Clk or negedge i_Rst_L)
  begin
    if (~i_Rst_L)
    begin
      o_SPI_MOSI     <= 1'b0;
      r_TX_Bit_Count <= 3'b111; // send MSb first
    end
    else
    begin
      // If ready is high, reset bit counts to default
      if (o_TX_Ready)
      begin
        r_TX_Bit_Count <= 3'b111;
      end
      // Catch the case where we start transaction and CPHA = 0
      else if (r_TX_DV & ~w_CPHA)
      begin
        o_SPI_MOSI     <= r_TX_Byte[3'b111];
        r_TX_Bit_Count <= 3'b110;
      end
      else if ((r_Leading_Edge & w_CPHA) | (r_Trailing_Edge & ~w_CPHA))
      begin
        r_TX_Bit_Count <= r_TX_Bit_Count - 1'b1;
        o_SPI_MOSI     <= r_TX_Byte[r_TX_Bit_Count];
      end
    end
  end


  // Purpose: Read in MISO data.
  always @(posedge i_Clk or negedge i_Rst_L)
  begin
    if (~i_Rst_L)
    begin
      o_RX_Byte      <= 8'h00;
      o_RX_DV        <= 1'b0;
      r_RX_Bit_Count <= 3'b111;
    end
    else
    begin

      // Default Assignments
      o_RX_DV   <= 1'b0;

      if (o_TX_Ready) // Check if ready is high, if so reset bit count to default
      begin
        r_RX_Bit_Count <= 3'b111;
      end
      else if ((r_Leading_Edge & ~w_CPHA) | (r_Trailing_Edge & w_CPHA))
      begin
        o_RX_Byte[r_RX_Bit_Count] <= i_SPI_MISO;  // Sample data
        r_RX_Bit_Count            <= r_RX_Bit_Count - 1'b1;
        if (r_RX_Bit_Count == 3'b000)
        begin
          o_RX_DV   <= 1'b1;   // Byte done, pulse Data Valid
        end
      end
    end
  end
  
  
  // Purpose: Add clock delay to signals for alignment.
  always @(posedge i_Clk or negedge i_Rst_L)
  begin
    if (~i_Rst_L)
    begin
      o_SPI_Clk  <= w_CPOL;
    end
    else
      begin
        o_SPI_Clk <= r_SPI_Clk;
      end // else: !if(~i_Rst_L)
  end // always @ (posedge i_Clk or negedge i_Rst_L)
  

endmodule // SPI_Master

SPI/tb.v
module tb();

parameter SPI_MODE = 0;
parameter CLKS_PER_HALF_BIT = 2;

integer i;
reg i_Rst_L;
reg i_Clk;

reg [7:0] i_TX_Byte;
reg i_TX_DV;
reg i_SPI_MISO;

wire o_TX_Ready;
wire o_RX_DV;
wire [7:0] o_RX_Byte;

wire o_SPI_Clk;
wire o_SPI_MOSI;

// module instantiation

SPI_Master UUT(i_Rst_L, i_Clk, i_TX_Byte, i_TX_DV, o_TX_Ready, o_RX_DV, o_RX_Byte, o_SPI_Clk, i_SPI_MISO, o_SPI_MOSI);

initial begin 
    i_Clk = 0;
    forever i_Clk = #5 ~i_Clk;
end

// dumpfile
initial begin
    $dumpfile("tb.vcd");
    $dumpvars(0, tb);
end

initial begin

    #0 i_Rst_L = 0; i_TX_Byte = 8'hAB; i_TX_DV = 1'b1;
    #10 i_Rst_L = 0;

    for (i = 0; i < 8; i = i + 1) begin
        i_TX_DV = 1'b1;
        i_SPI_MISO = ($random%2);
        @(posedge i_Clk);
    end

    #10 i_Rst_L = 0; i_TX_Byte = 8'h56; i_TX_DV = 1'b1;
    #10 i_Rst_L = 0;

    for (i = 0; i < 8; i = i + 1) begin
        i_TX_DV = 1'b1;
        i_SPI_MISO = ($random%2);
        @(posedge i_Clk);
    end

    #100 $finish;
end




endmodule

SPI/tb.vcd
$date
	Sat Apr  1 14:29:57 2023
$end
$version
	Icarus Verilog
$end
$timescale
	1s
$end
$scope module tb $end
$var wire 1 ! o_TX_Ready $end
$var wire 1 " o_SPI_MOSI $end
$var wire 1 # o_SPI_Clk $end
$var wire 1 $ o_RX_DV $end
$var wire 8 % o_RX_Byte [7:0] $end
$var reg 1 & i_Clk $end
$var reg 1 ' i_Rst_L $end
$var reg 1 ( i_SPI_MISO $end
$var reg 8 ) i_TX_Byte [7:0] $end
$var reg 1 * i_TX_DV $end
$var integer 32 + i [31:0] $end
$scope module UUT $end
$var wire 1 & i_Clk $end
$var wire 1 ' i_Rst_L $end
$var wire 1 ( i_SPI_MISO $end
$var wire 8 , i_TX_Byte [7:0] $end
$var wire 1 * i_TX_DV $end
$var wire 1 - w_CPHA $end
$var wire 1 . w_CPOL $end
$var reg 8 / o_RX_Byte [7:0] $end
$var reg 1 $ o_RX_DV $end
$var reg 1 # o_SPI_Clk $end
$var reg 1 " o_SPI_MOSI $end
$var reg 1 ! o_TX_Ready $end
$var reg 1 0 r_Leading_Edge $end
$var reg 3 1 r_RX_Bit_Count [2:0] $end
$var reg 1 2 r_SPI_Clk $end
$var reg 2 3 r_SPI_Clk_Count [1:0] $end
$var reg 5 4 r_SPI_Clk_Edges [4:0] $end
$var reg 3 5 r_TX_Bit_Count [2:0] $end
$var reg 8 6 r_TX_Byte [7:0] $end
$var reg 1 7 r_TX_DV $end
$var reg 1 8 r_Trailing_Edge $end
$upscope $end
$upscope $end
$enddefinitions $end
#0
$dumpvars
08
07
b0 6
b111 5
b0 4
b0 3
02
b111 1
00
b0 /
0.
0-
b10101011 ,
bx +
1*
b10101011 )
x(
0'
0&
b0 %
0$
0#
0"
0!
$end
#5
1&
#10
0&
0(
b0 +
#15
1(
b1 +
1&
#20
0&
#25
b10 +
1&
#30
0&
#35
b11 +
1&
#40
0&
#45
b100 +
1&
#50
0&
#55
b101 +
1&
#60
0&
#65
b110 +
1&
#70
0&
#75
0(
b111 +
1&
#80
0&
#85
b1000 +
1&
#90
0&
#95
1&
b1010110 )
b1010110 ,
#100
0&
#105
1&
1(
b1 +
#110
0&
#115
0(
b10 +
1&
#120
0&
#125
1(
b11 +
1&
#130
0&
#135
b100 +
1&
#140
0&
#145
0(
b101 +
1&
#150
0&
#155
1(
b110 +
1&
#160
0&
#165
0(
b111 +
1&
#170
0&
#175
b1000 +
1&
