SPI/spi_m.v
/*
SPI_MODE can be 0..3. configuration of one of 4 modes is based on 
CPOL(Clock POLarity): default value of the spi_clk when the bus is idle
CPHA(Clock PHAse): determines which edge of the clk data is sampled
CLKS_PER_HALF_BIT: set the integer number of clks for each half-bit of SPI data

we would be creating 25 KHz SPI_clk
i_clk let's say is 100MHZ


CPOL: Clock Polarity
CPOL=0 means clock idles at 0, leading edge is rising edge
CPOL=1 means clock idles at 1, leading edge is falling edge

CPHA: Clock Phase
CPHA=0 means the "out" side changes data- trailing edge
             the "in" side captures data- leading edge 
CPHA=1 means the "out" side changes data- leading edge
             the "in" side captures data- trailing edge
*/

`default_nettype none
module spiMaster(i_reset, i_clk, i_tx_data, i_tx_valid, 
o_tx_ready, o_rx_valid, o_rx_data, o_spi_clk, i_spi_MISO, o_spi_MOSI);


parameter DATAWIDTH = 8;
parameter SPI_MODE = 0;
parameter CLKS_PER_HALF_BIT = 2;

//control/data signals
input wire i_reset;
input wire i_clk;

// TX (MOSI) 
input wire [DATAWIDTH-1:0] i_tx_data;
input wire i_tx_valid;  // valid pulse with i_tx_data
output reg o_tx_ready;  // transmit ready for next byte


// RX (MISO)
output reg o_rx_valid; // data valid pulse
output reg [DATAWIDTH-1:0] o_rx_data; 


// SPI interface (all runs at spi clk domain)
output reg o_spi_clk;
input wire i_spi_MISO;
output reg o_spi_MOSI;

// all runs are w.r.t to spi clk domain
// r_*_* is registering the incoming data

wire w_CPOL;
wire w_CPHA;
reg [$clog2(CLKS_PER_HALF_BIT*2)-1:0] r_spi_clk_count;
reg r_spi_clk;
reg [4:0] r_spi_clk_edges;
reg r_leading_edge;
reg r_trailing_edge;
reg r_tx_valid;
reg [DATAWIDTH-1:0] r_tx_data;

reg [2:0] r_tx_bit_count;
reg [2:0] r_rx_bit_count;

assign w_CPOL = (SPI_MODE == 2) | (SPI_MODE == 3);
assign w_CPHA = (SPI_MODE == 1) | (SPI_MODE == 3);
// let's generate spi_clk
// spiClk SCK(i_clk, i_reset, i_tx_valid, o_tx_ready, o_spi_clk);
always @(posedge i_clk)begin
    if (i_reset) begin
        o_tx_ready <= 1'b0;
        r_spi_clk_edges <= 5'b0;
        r_leading_edge <= 1'b0;
        r_trailing_edge <= 1'b0;
        r_spi_clk <= w_CPOL;
        r_spi_clk_count <= 0;

    end
    else begin

        r_leading_edge <= 1'b0;
        r_trailing_edge <= 1'b0;

        if (i_tx_valid) begin
            o_tx_ready <= 1'b0;
            r_spi_clk_edges <= 16; // total edges are always 16
        end

        else if (r_spi_clk_edges > 0) begin
            o_tx_ready <= 1'b0;
            r_spi_clk_edges <= r_spi_clk_edges - 1;
            
            if (r_spi_clk_count == CLKS_PER_HALF_BIT*2-1) begin 
                r_trailing_edge <= 1;
                r_spi_clk_count <= 0;
                r_spi_clk <= ~r_spi_clk;
            end
            else if (r_spi_clk_count == CLKS_PER_HALF_BIT-1) begin
                r_leading_edge <= 1'b1;
                r_spi_clk_count <= r_spi_clk_count + 1;
                r_spi_clk <= ~r_spi_clk;
            end
            else begin
                r_spi_clk_count <= r_spi_clk_count + 1;
        end
        end
        else begin
            o_tx_ready <= 1;
        end
    end
end

// register i_tx_data when data is valid
always @(posedge i_clk) begin
    if (i_reset) begin
        r_tx_data <= 8'b0;
        r_tx_valid <= 1'b0;
    end

    else begin
        r_tx_valid <= i_tx_valid; // 1 clk cycle delay
        if (i_tx_valid)
        begin
            r_tx_data <= i_tx_data;
        end
    end
end

// MOSI data
always @(posedge i_clk) begin
    if (i_reset) begin
        o_spi_MOSI <= 1'b0;
        r_tx_bit_count <= 3'b111; // MSB first
    end
    else begin
        if (o_tx_ready) 
            r_tx_bit_count <= 3'b111;
        else if (r_tx_valid & ~w_CPHA) begin
            o_spi_MOSI <= r_tx_data[7];
            r_tx_bit_count <= 3'b110;
        end
        else if ((r_leading_edge & w_CPHA) | (r_trailing_edge & ~w_CPHA)) begin
            r_tx_bit_count <= r_tx_bit_count - 1;
            o_spi_MOSI <= r_tx_data[r_tx_bit_count];
        end
    end
end

// read MISO data
always @(posedge i_clk) begin
    if (i_reset) begin
        o_rx_data <= 8'b0;
        o_rx_valid <= 0;
        r_rx_bit_count <= 3'b111;
    end
    else begin
        // default assignment
        o_rx_valid <= 0; // goes high, saying we have received the byte

        if (o_tx_ready) begin
            r_rx_bit_count <= 3'b111;
        end
        else if ((r_leading_edge & ~w_CPHA) | (r_trailing_edge & w_CPHA)) begin
            o_rx_data[r_rx_bit_count] <= i_spi_MISO; //sample data
            r_rx_bit_count <= r_rx_bit_count - 1;

        if (r_rx_bit_count == 3'b000) begin
            o_rx_valid <= 1;
        end
        end
    end
end

// maybe to be extra sure that clk is synced properly
always @(posedge i_clk) begin
    if (i_reset) 
        o_spi_clk <= w_CPOL;
    else 
        o_spi_clk <= r_spi_clk;
end


endmodule

SPI/tb_spiM.v
module tb_spiM();

integer i;
parameter SPI_MODE = 0;
parameter CLKS_PER_HALF_BIT = 2;
parameter MAIN_CLK_DELAY = 5;
parameter DATAWIDTH = 8;

reg i_reset;
reg i_clk;

//Master Specific
reg [DATAWIDTH-1:0] i_tx_data;
reg i_tx_valid;
reg i_spi_MISO;


wire o_spi_clk;
wire o_spi_MOSI;
wire o_tx_ready;
wire o_rx_valid;
wire [DATAWIDTH-1:0] o_rx_data;

// module instantiation
spiMaster UUT(i_reset, i_clk, i_tx_data, i_tx_valid, o_tx_ready, o_rx_valid, o_rx_data, o_spi_clk, i_spi_MISO, o_spi_MOSI);

initial begin 
    i_clk = 0;
    forever i_clk = #5 !i_clk;
end

// dumpfile
initial begin
    $dumpfile("tb_spiM.vcd");
    $dumpvars(0, tb_spiM);
end

initial begin

    #0 i_reset = 1; i_tx_data = 8'hAB; i_tx_valid = 1'b0;
    #10 i_reset = 0; 

    for (i = 0; i < 16; i = i + 1) begin
        i_tx_valid = 1'b1;
        i_spi_MISO = ($random%2);
        @(posedge i_clk);
    end
    #100 $finish;
end


endmodule

SPI/tb_spiM.vcd
$date
	Sun Mar 26 20:53:26 2023
$end
$version
	Icarus Verilog
$end
$timescale
	1s
$end
$scope module tb_spiM $end
$var wire 1 ! o_tx_ready $end
$var wire 1 " o_spi_clk $end
$var wire 1 # o_spi_MOSI $end
$var wire 1 $ o_rx_valid $end
$var wire 8 % o_rx_data [7:0] $end
$var reg 1 & i_clk $end
$var reg 1 ' i_reset $end
$var reg 1 ( i_spi_MISO $end
$var reg 8 ) i_tx_data [7:0] $end
$var reg 1 * i_tx_valid $end
$var integer 32 + i [31:0] $end
$scope module UUT $end
$var wire 1 & i_clk $end
$var wire 1 ' i_reset $end
$var wire 1 ( i_spi_MISO $end
$var wire 8 , i_tx_data [7:0] $end
$var wire 1 * i_tx_valid $end
$var wire 1 - w_CPHA $end
$var wire 1 . w_CPOL $end
$var reg 8 / o_rx_data [7:0] $end
$var reg 1 $ o_rx_valid $end
$var reg 1 # o_spi_MOSI $end
$var reg 1 " o_spi_clk $end
$var reg 1 ! o_tx_ready $end
$var reg 1 0 r_leading_edge $end
$var reg 3 1 r_rx_bit_count [2:0] $end
$var reg 1 2 r_spi_clk $end
$var reg 2 3 r_spi_clk_count [1:0] $end
$var reg 5 4 r_spi_clk_edges [4:0] $end
$var reg 1 5 r_trailing_edge $end
$var reg 3 6 r_tx_bit_count [2:0] $end
$var reg 8 7 r_tx_data [7:0] $end
$var reg 1 8 r_tx_valid $end
$upscope $end
$upscope $end
$enddefinitions $end
#0
$dumpvars
x8
bx 7
bx 6
x5
bx 4
bx 3
x2
bx 1
x0
bx /
0.
0-
b10101011 ,
bx +
0*
b10101011 )
x(
1'
0&
bx %
x$
x#
x"
x!
$end
#5
b0 3
02
05
00
b0 4
0!
08
b0 7
b111 6
0#
b111 1
0$
b0 %
b0 /
0"
1&
#10
0&
0(
1*
b0 +
0'
#15
b10101011 7
18
b10000 4
1(
b1 +
1&
#20
0&
#25
b110 6
1#
b10 +
1&
#30
0&
#35
b11 +
1&
#40
0&
#45
b100 +
1&
#50
0&
#55
b101 +
1&
#60
0&
#65
b110 +
1&
#70
0&
#75
0(
b111 +
1&
#80
0&
#85
1(
b1000 +
1&
#90
0&
#95
b1001 +
1&
#100
0&
#105
0(
b1010 +
1&
#110
0&
#115
1(
b1011 +
1&
#120
0&
#125
b1100 +
1&
#130
0&
#135
0(
b1101 +
1&
#140
0&
#145
1(
b1110 +
1&
#150
0&
#155
0(
b1111 +
1&
#160
0&
#165
b10000 +
1&
